interpboard/__init__.py
interpboard/cli.py
interpboard/config.py
interpboard/utils.py
interpboard/attribution/__init__.py
interpboard/attribution/attention_rollout.py
interpboard/attribution/gradients.py
interpboard/attribution/viz.py
interpboard/circuits/__init__.py
interpboard/circuits/head_ablation.py
interpboard/circuits/logit_lens.py
interpboard/circuits/neuron_analysis.py
interpboard/dashboards/__init__.py
interpboard/patching/__init__.py
interpboard/patching/activ_patch.py
interpboard/patching/causal_tracing.py
interpboard/patching/utils.py
interpboard/visualization/__init__.py
interpboard/visualization/heatmap.py
interpboard/visualization/text_overlay.py
interpboard/visualization/styles/default.css
interpboard-0.1.1.dist-info/licenses/LICENSE
interpboard-0.1.1.dist-info/METADATA
interpboard-0.1.1.dist-info/WHEEL
interpboard-0.1.1.dist-info/entry_points.txt
interpboard-0.1.1.dist-info/top_level.txt
interpboard-0.1.1.dist-info/RECORD
