Metadata-Version: 2.4
Name: interpboard
Version: 0.1.1
Summary: A comprehensive toolkit for interpreting and understanding large language models
Home-page: https://github.com/sohv/interpboard
Author: Sohan Venkatesh
Author-email: Sohan Venkatesh <soh.venkatesh@gmail.com>
License: MIT
Project-URL: Homepage, https://github.com/sohv/interpboard
Project-URL: Documentation, https://github.com/sohv/interpboard/blob/main/README.md
Project-URL: Repository, https://github.com/sohv/interpboard.git
Project-URL: Bug Tracker, https://github.com/sohv/interpboard/issues
Project-URL: Changelog, https://github.com/sohv/interpboard/blob/main/CHANGELOG.md
Keywords: machine-learning,interpretability,transformers,llm,visualization,mechanistic-interpretability,attention-analysis,gradient-attribution
Classifier: Development Status :: 3 - Alpha
Classifier: Intended Audience :: Developers
Classifier: Intended Audience :: Science/Research
Classifier: License :: OSI Approved :: MIT License
Classifier: Operating System :: OS Independent
Classifier: Programming Language :: Python :: 3
Classifier: Programming Language :: Python :: 3.8
Classifier: Programming Language :: Python :: 3.9
Classifier: Programming Language :: Python :: 3.10
Classifier: Programming Language :: Python :: 3.11
Classifier: Programming Language :: Python :: 3.12
Classifier: Topic :: Scientific/Engineering :: Artificial Intelligence
Classifier: Topic :: Scientific/Engineering :: Visualization
Classifier: Topic :: Software Development :: Libraries :: Python Modules
Requires-Python: >=3.8
License-File: LICENSE
Requires-Dist: torch>=1.13.0
Requires-Dist: transformers>=4.20.0
Requires-Dist: numpy>=1.21.0
Requires-Dist: matplotlib>=3.5.0
Requires-Dist: seaborn>=0.11.0
Requires-Dist: plotly>=5.0.0
Requires-Dist: rich>=12.0.0
Requires-Dist: termcolor>=1.1.0
Requires-Dist: pandas>=1.3.0
Requires-Dist: scipy>=1.7.0
Requires-Dist: tqdm>=4.62.0
Requires-Dist: einops>=0.6.0
Provides-Extra: web
Requires-Dist: streamlit>=1.20.0; extra == "web"
Requires-Dist: gradio>=3.0.0; extra == "web"
Provides-Extra: jupyter
Requires-Dist: ipywidgets>=7.6.0; extra == "jupyter"
Requires-Dist: jupyter>=1.0.0; extra == "jupyter"
Requires-Dist: notebook>=6.4.0; extra == "jupyter"
Provides-Extra: dev
Requires-Dist: pytest>=6.0; extra == "dev"
Requires-Dist: pytest-cov>=2.0; extra == "dev"
Requires-Dist: black>=22.0; extra == "dev"
Requires-Dist: flake8>=4.0; extra == "dev"
Requires-Dist: mypy>=0.910; extra == "dev"
Requires-Dist: pre-commit>=2.15.0; extra == "dev"
Requires-Dist: isort>=5.10.0; extra == "dev"
Requires-Dist: ruff>=0.0.261; extra == "dev"
Provides-Extra: docs
Requires-Dist: sphinx>=4.0; extra == "docs"
Requires-Dist: sphinx-rtd-theme>=1.0; extra == "docs"
Requires-Dist: myst-parser>=0.17.0; extra == "docs"
Requires-Dist: sphinxcontrib-napoleon>=0.7; extra == "docs"
Provides-Extra: test
Requires-Dist: pytest>=6.0; extra == "test"
Requires-Dist: pytest-cov>=2.0; extra == "test"
Requires-Dist: pytest-mock>=3.6.0; extra == "test"
Requires-Dist: hypothesis>=6.0.0; extra == "test"
Provides-Extra: performance
Requires-Dist: accelerate>=0.20.0; extra == "performance"
Requires-Dist: deepspeed>=0.9.0; extra == "performance"
Provides-Extra: all
Requires-Dist: interpboard[dev,docs,jupyter,performance,test,web]; extra == "all"
Dynamic: author
Dynamic: home-page
Dynamic: license-file
Dynamic: requires-python
